batch_sqs_broker/__init__.py
batch_sqs_broker/broker.py
dramatiq_sqs_batch-1.0.0.dist-info/LICENSE
dramatiq_sqs_batch-1.0.0.dist-info/METADATA
dramatiq_sqs_batch-1.0.0.dist-info/WHEEL
dramatiq_sqs_batch-1.0.0.dist-info/RECORD
