Metadata-Version: 2.1
Name: dramatiq_sqs_batch
Version: 1.0.0
Summary: A high-performance batch processing broker for AWS SQS with intelligent message splitting
Home-page: https://github.com/jiayun/dramatiq_sqs_batch
License: MIT
Keywords: aws,sqs,dramatiq,message-queue,batch-processing
Author: Jiayun Zhou
Author-email: jiayun@gmail.com
Requires-Python: >=3.8.1,<4.0.0
Classifier: Development Status :: 5 - Production/Stable
Classifier: Intended Audience :: Developers
Classifier: License :: OSI Approved :: MIT License
Classifier: Programming Language :: Python :: 3
Classifier: Programming Language :: Python :: 3.9
Classifier: Programming Language :: Python :: 3.10
Classifier: Programming Language :: Python :: 3.11
Classifier: Programming Language :: Python :: 3.12
Classifier: Programming Language :: Python :: 3.13
Classifier: Programming Language :: Python :: 3.8
Classifier: Topic :: Software Development :: Libraries :: Python Modules
Classifier: Topic :: System :: Distributed Computing
Requires-Dist: boto3 (>=1.20.0,<2.0.0)
Requires-Dist: dramatiq (>=1.12.0,<2.0.0)
Requires-Dist: dramatiq-sqs (>=0.2.0,<0.3.0)
Project-URL: Documentation, https://github.com/jiayun/dramatiq_sqs_batch/blob/main/README.md
Project-URL: Repository, https://github.com/jiayun/dramatiq_sqs_batch
